Lib/site-packages/_distutils_hack/__init__.py
Lib/site-packages/_distutils_hack/override.py
Lib/site-packages/build/__init__.py
Lib/site-packages/build/__main__.py
Lib/site-packages/build/_builder.py
Lib/site-packages/build/_ctx.py
Lib/site-packages/build/_exceptions.py
Lib/site-packages/build/_types.py
Lib/site-packages/build/_util.py
Lib/site-packages/build/env.py
Lib/site-packages/build/py.typed
Lib/site-packages/build/util.py
Lib/site-packages/build/_compat/__init__.py
Lib/site-packages/build/_compat/importlib.py
Lib/site-packages/build/_compat/tarfile.py
Lib/site-packages/build/_compat/tomllib.py
Lib/site-packages/certifi/__init__.py
Lib/site-packages/certifi/__main__.py
Lib/site-packages/certifi/core.py
Lib/site-packages/certifi/py.typed
Lib/site-packages/charset_normalizer/__init__.py
Lib/site-packages/charset_normalizer/__main__.py
Lib/site-packages/charset_normalizer/api.py
Lib/site-packages/charset_normalizer/cd.py
Lib/site-packages/charset_normalizer/constant.py
Lib/site-packages/charset_normalizer/legacy.py
Lib/site-packages/charset_normalizer/md.py
Lib/site-packages/charset_normalizer/models.py
Lib/site-packages/charset_normalizer/py.typed
Lib/site-packages/charset_normalizer/utils.py
Lib/site-packages/charset_normalizer/version.py
Lib/site-packages/charset_normalizer/cli/__init__.py
Lib/site-packages/charset_normalizer/cli/__main__.py
Lib/site-packages/colorama/__init__.py
Lib/site-packages/colorama/ansi.py
Lib/site-packages/colorama/ansitowin32.py
Lib/site-packages/colorama/initialise.py
Lib/site-packages/colorama/win32.py
Lib/site-packages/colorama/winterm.py
Lib/site-packages/colorama/tests/__init__.py
Lib/site-packages/colorama/tests/ansi_test.py
Lib/site-packages/colorama/tests/ansitowin32_test.py
Lib/site-packages/colorama/tests/initialise_test.py
Lib/site-packages/colorama/tests/isatty_test.py
Lib/site-packages/colorama/tests/utils.py
Lib/site-packages/colorama/tests/winterm_test.py
Lib/site-packages/docutils/__init__.py
pgeng-1.8.5.dist-info/licenses/LICENSE
pgeng-1.8.5.dist-info/METADATA
pgeng-1.8.5.dist-info/WHEEL
pgeng-1.8.5.dist-info/top_level.txt
pgeng-1.8.5.dist-info/RECORD
